README.md
setup.py
flask_notifyAll/__init__.py
flask_notifyAll/core.py
flask_notifyAll/errors.py
flask_notifyAll/helpers.py
flask_notifyAll.egg-info/PKG-INFO
flask_notifyAll.egg-info/SOURCES.txt
flask_notifyAll.egg-info/dependency_links.txt
flask_notifyAll.egg-info/requires.txt
flask_notifyAll.egg-info/top_level.txt