Metadata-Version: 1.1
Name: flask-notifyAll
Version: 1.0.2
Summary: Simple tool which will provide sms and email notifications
Home-page: https://github.com/MichaelYusko/flask-notifyAll
Author: Mike Yusko
Author-email: freshjelly12@yahoo.com
License: MIT
Keywords: flask,sms,notifications,email,send
Platform: UNKNOWN
Classifier: Development Status :: 5 - Production/Stable
Classifier: Environment :: Web Environment
Classifier: Programming Language :: Python :: 3.5
Classifier: License :: OSI Approved :: MIT License
